README.md
setup.py
gaussian_binomial_probability/Binomialdistribution.py
gaussian_binomial_probability/Gaussiandistribution.py
gaussian_binomial_probability/Generaldistribution.py
gaussian_binomial_probability/__init__.py
gaussian_binomial_probability.egg-info/PKG-INFO
gaussian_binomial_probability.egg-info/SOURCES.txt
gaussian_binomial_probability.egg-info/dependency_links.txt
gaussian_binomial_probability.egg-info/not-zip-safe
gaussian_binomial_probability.egg-info/top_level.txt