Metadata-Version: 1.0
Name: gaussian-binomial-probability
Version: 0.1
Summary: Gaussian and Binomial distributions
Home-page: https://gitlab.com/chinh-dev11/python-opp-modularize/-/tree/lab/5_exercise_upload_to_pypi
Author: Chinh Le
Author-email: chinh.tester11@gmail.com
License: UNKNOWN
Platform: UNKNOWN
